{
  "$comment": "Generated by npm run enrich:firmwares. Do not edit by hand; edit firmware.yaml for authored data.",
  "popularity": {
    "githubStars": 106,
    "githubForks": 26,
    "githubWatchers": 8,
    "githubOpenIssues": 14,
    "githubContributors": 13,
    "releaseDownloads": 3863,
    "latestReleaseDownloads": 177,
    "lastChecked": "2026-07-09"
  },
  "verification": {
    "sourceAvailable": true,
    "releasesAvailable": true,
    "ciBuilds": true,
    "lastChecked": "2026-07-09"
  }
}
