{
  "$comment": "Generated by npm run enrich:firmwares. Do not edit by hand; edit firmware.yaml for authored data.",
  "popularity": {
    "githubStars": 3188,
    "githubForks": 1079,
    "githubWatchers": 59,
    "githubOpenIssues": 846,
    "githubContributors": 174,
    "releaseDownloads": 1561816,
    "latestReleaseDownloads": 5683,
    "lastChecked": "2026-07-05"
  },
  "verification": {
    "sourceAvailable": true,
    "releasesAvailable": true,
    "ciBuilds": true,
    "lastChecked": "2026-07-05"
  }
}
