{
  "$comment": "Generated by npm run enrich:firmwares. Do not edit by hand; edit firmware.yaml for authored data.",
  "popularity": {
    "githubStars": 7,
    "githubForks": 0,
    "githubWatchers": 0,
    "githubOpenIssues": 0,
    "githubContributors": 3,
    "releaseDownloads": 78,
    "latestReleaseDownloads": 23,
    "lastChecked": "2026-07-05"
  },
  "verification": {
    "sourceAvailable": true,
    "releasesAvailable": true,
    "ciBuilds": false,
    "lastChecked": "2026-07-05"
  }
}
